Metadata-Version: 2.1
Name: browser-dog
Version: 0.0.1
Summary: chrome selenium browser by cookies
Home-page: https://www.linkedin.com/in/chandlersong/
Author: chandler song
Author-email: 275737875@qq.com
License: MIT
Keywords: selenium automation browser cookies
Platform: all
Classifier: Intended Audience :: Developers
Classifier: Operating System :: OS Independent
Classifier: Natural Language :: Chinese (Simplified)
Classifier: Programming Language :: Python :: 3.7
Classifier: Programming Language :: Python :: 3.8
Classifier: Programming Language :: Python :: 3.9
Classifier: Programming Language :: Python :: 3.10
Classifier: Topic :: Software Development :: Libraries
License-File: LICENSE
